MANIFEST.in
README.md
setup.py
ManipulateAggregates/__init__.py
ManipulateAggregates.egg-info/PKG-INFO
ManipulateAggregates.egg-info/SOURCES.txt
ManipulateAggregates.egg-info/dependency_links.txt
ManipulateAggregates.egg-info/entry_points.txt
ManipulateAggregates.egg-info/requires.txt
ManipulateAggregates.egg-info/top_level.txt
ManipulateAggregates/aggregate/__init__.py
ManipulateAggregates/aggregate/hlb.py
ManipulateAggregates/aggregate/visualize.py
ManipulateAggregates/bin/__init__.py
ManipulateAggregates/bin/energyscan.py
ManipulateAggregates/bin/hashsort.py
ManipulateAggregates/bin/manipagg.py
ManipulateAggregates/collection/__init__.py
ManipulateAggregates/collection/hashIO.py
ManipulateAggregates/collection/p2p3IO.py
ManipulateAggregates/collection/read.py
ManipulateAggregates/collection/write.py
ManipulateAggregates/collection/gnuplot/__init__.py
ManipulateAggregates/collection/gnuplot/gpcsv.py
ManipulateAggregates/collection/gnuplot/postprocess.py
ManipulateAggregates/collection/opengl/__init__.py
ManipulateAggregates/data/anthracene.cfg
ManipulateAggregates/data/anthracene.xyz
ManipulateAggregates/data/dye5.molden
ManipulateAggregates/data/porphin.cfg
ManipulateAggregates/data/porphin.xyz
ManipulateAggregates/data/urea.cfg
ManipulateAggregates/data/urea.xyz
ManipulateAggregates/energyscan/__init__.py
ManipulateAggregates/energyscan/ansilliary.py
ManipulateAggregates/energyscan/minimasearch.py
ManipulateAggregates/energyscan/scan.py
ManipulateAggregates/energyscan/similarityscreening.py
ManipulateAggregates/orbitalcharacter/Smatrix.py
ManipulateAggregates/orbitalcharacter/__init__.py
ManipulateAggregates/orbitalcharacter/read_MO_basis.py