Metadata-Version: 2.1
Name: ManipulateAggregates
Version: 0.1.3
Summary: Manipulate molecular DOF and scan PES of aggregates
Home-page: https://github.com/razziel89/ManipulateAggregates
Author: Torsten Sachse
License: UNKNOWN
Platform: UNKNOWN
Classifier: Development Status :: 4 - Beta
Classifier: Environment :: Console
Classifier: Intended Audience :: Developers
Classifier: Intended Audience :: Science/Research
Classifier: License :: OSI Approved :: GNU General Public License v3 or later (GPLv3+)
Classifier: Natural Language :: English
Classifier: Operating System :: POSIX :: Linux
Classifier: Programming Language :: C++
Classifier: Programming Language :: Python :: 3.8
Classifier: Programming Language :: Python :: 3 :: Only
